terminator3/__init__.py
terminator3/main.py
terminator3/metadata.py
terminator3-0.0.1.dist-info/LICENSE
terminator3-0.0.1.dist-info/METADATA
terminator3-0.0.1.dist-info/WHEEL
terminator3-0.0.1.dist-info/entry_points.txt
terminator3-0.0.1.dist-info/top_level.txt
terminator3-0.0.1.dist-info/RECORD
